minireload/__init__.py
minireload/autoreload.py
minireload/reloader.py
minireload-0.0.9.dist-info/LICENSE
minireload-0.0.9.dist-info/METADATA
minireload-0.0.9.dist-info/WHEEL
minireload-0.0.9.dist-info/top_level.txt
minireload-0.0.9.dist-info/RECORD
