Metadata-Version: 2.1
Name: minireload
Version: 0.0.9
Summary: Small library for live code reloading
Author-email: Jona Ruof <jona.ruof@uni-ulm.de>
Project-URL: Homepage, https://github.com/joruof/minireload
Project-URL: Bug Tracker, https://github.com/joruof/minireload/issues
Classifier: Programming Language :: Python :: 3
Requires-Python: >=3.6
License-File: LICENSE
Requires-Dist: watchdog >=4.0.0
